perceptron/__init__.py
perceptron/artificial_neuron.py
python_perceptron-0.1.0.dist-info/METADATA
python_perceptron-0.1.0.dist-info/WHEEL
python_perceptron-0.1.0.dist-info/top_level.txt
python_perceptron-0.1.0.dist-info/RECORD
